{"name": "Pok\u00e9mon Omega Ruby/Alpha Sapphire", "developers": [], "image": "http://static.giantbomb.com/uploads/scale_medium/8/82063/2630130-rubysapphire.jpg", "deck": "A new Pok\u00e9mon adventure for Nintendo 3DS and 2DS. Omega Ruby and Alpha Sapphire are remakes of Pok\u00e9mon Ruby and Sapphire, respectively.", "publishers": [{"name": "Nintendo", "id": 591}], "platforms": [{"name": "Nintendo 3DS", "short": "3DS", "id": 103}, {"name": "Nintendo 3DS eShop", "short": "3DSE", "id": 123}], "id": 24328}