{"name": "Pok\u00e9mon Ranger", "developers": [{"name": "HAL Laboratory, Inc.", "id": 534}], "image": "http://static.giantbomb.com/uploads/scale_medium/8/87790/2171286-box_pkmnr.png", "deck": "In the first Pok\u00e9mon Ranger game, you play a Pok\u00e9mon Ranger in the Fiore region who must stop the Go-Rock Quads from taking control of powerful pok\u00e9mon and attacking the citizens of Fiore.  Using your 'Capture Stylus', you can capture wild pok\u00e9mon who can assist you in your journey.", "publishers": [], "platforms": [{"name": "Nintendo DS", "short": "DS", "id": 43}], "id": 14747}