{"name": "recycle", "contest_type": {"name": "smart", "url": "http://pokeapi.co/api/v2/contest-type/4/"}, "names": [{"name": "Recycle", "language": {"name": "en", "url": "http://pokeapi.co/api/v2/language/9/"}}, {"name": "Riciclo", "language": {"name": "it", "url": "http://pokeapi.co/api/v2/language/8/"}}, {"name": "Reciclaje", "language": {"name": "es", "url": "http://pokeapi.co/api/v2/language/7/"}}, {"name": "Aufbereitung", "language": {"name": "de", "url": "http://pokeapi.co/api/v2/language/6/"}}, {"name": "Recyclage", "language": {"name": "fr", "url": "http://pokeapi.co/api/v2/language/5/"}}, {"name": "\ub9ac\uc0ac\uc774\ud074", "language": {"name": "ko", "url": "http://pokeapi.co/api/v2/language/3/"}}, {"name": "\u30ea\u30b5\u30a4\u30af\u30eb", "language": {"name": "ja", "url": "http://pokeapi.co/api/v2/language/1/"}}], "contest_combos": null, "target": {"name": "user", "url": "http://pokeapi.co/api/v2/move-target/7/"}, "meta": {"min_hits": null, "max_hits": null, "stat_chance": 0, "min_turns": null, "flinch_chance": 0, "ailment": {"name": "none", "url": "http://pokeapi.co/api/v2/move-ailment/0/"}, "drain": 0, "max_turns": null, "category": {"name": "unique", "url": "http://pokeapi.co/api/v2/move-category/13/"}, "ailment_chance": 0, "healing": 0, "crit_rate": 0}, "power": null, "generation": {"name": "generation-iii", "url": "http://pokeapi.co/api/v2/generation/3/"}, "effect_chance": null, "contest_effect": {"url": "http://pokeapi.co/api/v2/contest-effect/17/"}, "effect_changes": [], "effect_entries": [{"short_effect": "User recovers the item it last used up.", "effect": "User recovers the last item consumed by the user or a Pok\u00e9mon in its position on the field.  The item must be used again before it can be recovered by this move again.  If the user is holding an item, this move fails.\n\nItems taken or given away by covet, knock off, switcheroo, thief, or trick may not be recovered.", "language": {"name": "en", "url": "http://pokeapi.co/api/v2/language/9/"}}], "damage_class": {"name": "status", "url": "http://pokeapi.co/api/v2/move-damage-class/1/"}, "accuracy": null, "priority": 0, "pp": 10, "stat_changes": [], "super_contest_effect": {"url": "http://pokeapi.co/api/v2/super-contest-effect/12/"}, "id": 278, "past_values": [], "type": {"name": "normal", "url": "http://pokeapi.co/api/v2/type/1/"}}