{"name": "confusion", "contest_type": {"name": "smart", "url": "http://pokeapi.co/api/v2/contest-type/4/"}, "names": [{"name": "Confusion", "language": {"name": "en", "url": "http://pokeapi.co/api/v2/language/9/"}}, {"name": "Confusione", "language": {"name": "it", "url": "http://pokeapi.co/api/v2/language/8/"}}, {"name": "Confusi\u00f3n", "language": {"name": "es", "url": "http://pokeapi.co/api/v2/language/7/"}}, {"name": "Konfusion", "language": {"name": "de", "url": "http://pokeapi.co/api/v2/language/6/"}}, {"name": "Choc Mental", "language": {"name": "fr", "url": "http://pokeapi.co/api/v2/language/5/"}}, {"name": "\uc5fc\ub3d9\ub825", "language": {"name": "ko", "url": "http://pokeapi.co/api/v2/language/3/"}}, {"name": "\u306d\u3093\u308a\u304d", "language": {"name": "ja", "url": "http://pokeapi.co/api/v2/language/1/"}}], "contest_combos": {"super": {"use_before": null, "use_after": null}, "normal": {"use_before": [{"name": "psychic", "url": "http://pokeapi.co/api/v2/move/94/"}, {"name": "teleport", "url": "http://pokeapi.co/api/v2/move/100/"}, {"name": "kinesis", "url": "http://pokeapi.co/api/v2/move/134/"}, {"name": "future-sight", "url": "http://pokeapi.co/api/v2/move/248/"}], "use_after": [{"name": "psychic", "url": "http://pokeapi.co/api/v2/move/94/"}, {"name": "kinesis", "url": "http://pokeapi.co/api/v2/move/134/"}, {"name": "calm-mind", "url": "http://pokeapi.co/api/v2/move/347/"}]}}, "target": {"name": "selected-pokemon", "url": "http://pokeapi.co/api/v2/move-target/10/"}, "meta": {"min_hits": null, "max_hits": null, "stat_chance": 0, "min_turns": 2, "flinch_chance": 0, "ailment": {"name": "confusion", "url": "http://pokeapi.co/api/v2/move-ailment/6/"}, "drain": 0, "max_turns": 5, "category": {"name": "damage+ailment", "url": "http://pokeapi.co/api/v2/move-category/4/"}, "ailment_chance": 10, "healing": 0, "crit_rate": 0}, "power": 50, "generation": {"name": "generation-i", "url": "http://pokeapi.co/api/v2/generation/1/"}, "effect_chance": 10, "contest_effect": {"url": "http://pokeapi.co/api/v2/contest-effect/9/"}, "effect_changes": [], "effect_entries": [{"short_effect": "Has a $effect_chance% chance to confuse the target.", "effect": "Inflicts regular damage.  Has a $effect_chance% chance to confuse the target.", "language": {"name": "en", "url": "http://pokeapi.co/api/v2/language/9/"}}], "damage_class": {"name": "special", "url": "http://pokeapi.co/api/v2/move-damage-class/3/"}, "accuracy": 100, "priority": 0, "pp": 25, "stat_changes": [], "super_contest_effect": {"url": "http://pokeapi.co/api/v2/super-contest-effect/5/"}, "id": 93, "past_values": [], "type": {"name": "psychic", "url": "http://pokeapi.co/api/v2/type/14/"}}